whoissearch/__init__.py
whoissearch/decompressor.py
whoissearch/downloader.py
whoissearch/logger.py
whoissearch/main.py
whoissearch/reader.py
whoissearch/searcher.py
whoissearch/writer.py
whoissearch/classifiers/__init__.py
whoissearch/classifiers/standardnetworkclassifier.py
whoissearch/data/__init__.py
whoissearch/data/standardnetwork.py
whoissearch/parsers/__init__.py
whoissearch/parsers/standardparser.py
whoissearch-0.1.0.dist-info/LICENSE
whoissearch-0.1.0.dist-info/METADATA
whoissearch-0.1.0.dist-info/WHEEL
whoissearch-0.1.0.dist-info/entry_points.txt
whoissearch-0.1.0.dist-info/top_level.txt
whoissearch-0.1.0.dist-info/RECORD
