Metadata-Version: 2.1
Name: whoissearch
Version: 0.1.0
Summary: Get network blocks from whois from a list of words
Home-page: https://github.com/hackliza/WhoisSearch
Author: Guzman Cernadas Perez
Author-email: guzman.cernadas@protonmail.com
License: UNKNOWN
Platform: UNKNOWN
Classifier: Programming Language :: Python :: 3
Classifier: License :: OSI Approved :: GNU General Public License v3 (GPLv3)
Requires-Dist: requests (~=2.25.0)
Requires-Dist: setuptools (>=50.3.2)
Requires-Dist: tqdm (>=4.53.0)
